<WndTap Name="xms_role" Text="xms_role" Ver="2">
<var name="refreshAfterEdit" expr="2"/>
<var name="dataRequired" expr=""/>
<var name="dataRequireless" expr=""/>
<xi:include href="lan\xms_role.xml" xmlns:xi="http://www.w3.org/2001/XInclude"/>
<Ctrls>
<GroupBox  Name="GBxms_role" id="xms_role" Text="xms_role" Size="100,100"><Ctrls>
<xi:include xmlns:xi="http://www.w3.org/2001/XInclude" href="xms_role_GBDEDIT.xml"/>
<BR AutoHeight="1"/><xi:include xmlns:xi="http://www.w3.org/2001/XInclude" href="xms_role_GBOPE.xml"/>
<xi:include xmlns:xi="http://www.w3.org/2001/XInclude" href="xms_role_Vh.xml"/></Ctrls></GroupBox></Ctrls>
	<OnChanged></OnChanged>
	<OnActivate><SetVisible name="insertxms_role" Visible="1"/><SetVisible name="modifyxms_role" Visible="0"/></OnActivate>
</WndTap>
