<Language name="xtmst_freight">
<Lang name="xtmst_freight" value="货运单"/>
<Lang name="uv_freightloadunloadop" value="装卸货"/>
<Lang name="SizeInfo" value="尺寸信息"/>
<Lang name="CheckInfo" value="检查信息"/>
<Lang name="DispatchInfo" value="派车信息"/>
<Lang name="TabEditxtmst_freight" value="xtmst_freight Edit"/>
<Lang name="TabViewxtmst_freight" value="xtmst_freight View"/>
<Lang name="freightcode" value="货运单号"/>
<Lang name="ttp_freightcode" value=""/>
<Lang name="customerorderid" value="客户单号"/>
<Lang name="ttp_customerorderid" value=""/>
<Lang name="vehiclerealtimeid" value="发车班次"/>
<Lang name="ttp_vehiclerealtimeid" value=""/>
<Lang name="issealbox" value="是否封箱"/>
<Lang name="ttp_issealbox" value=""/>
<Lang name="volumn" value="体积"/>
<Lang name="ttp_volumn" value=""/>
<Lang name="weight" value="重量"/>
<Lang name="ttp_weight" value=""/>
<Lang name="amount" value="件数"/>
<Lang name="ttp_amount" value=""/>
<Lang name="deliverymode" value=""/>
<Lang name="ttp_deliverymode" value=""/>
<Lang name="consignmentmode" value=""/>
<Lang name="ttp_consignmentmode" value=""/>
<Lang name="datelimite" value="送货/收货时间限制(天)"/>
<Lang name="ttp_datelimite" value=""/>
<Lang name="expectbegindatetime" value="预计起始时间"/>
<Lang name="ttp_expectbegindatetime" value=""/>
<Lang name="expectenddatetime" value="预计送达时间"/>
<Lang name="ttp_expectenddatetime" value=""/>
<Lang name="isbackorder" value="是否回单"/>
<Lang name="ttp_isbackorder" value=""/>
<Lang name="status" value=""/>
<Lang name="ttp_status" value=""/>
<Lang name="checkdate" value="确认时间"/>
<Lang name="ttp_checkdate" value=""/>
<Lang name="checkby" value="确认人"/>
<Lang name="ttp_checkby" value=""/>
<Lang name="isdispatchcarrier" value=""/>
<Lang name="ttp_isdispatchcarrier" value=""/>
<Lang name="ischeck" value="是否确认"/>
<Lang name="ttp_ischeck" value=""/>
<Lang name="actualweight" value="实际重量"/>
<Lang name="ttp_actualweight" value=""/>
<Lang name="actualvolumn" value="实际体积"/>
<Lang name="ttp_actualvolumn" value=""/>
<Lang name="actualamount" value="实际数量"/>
<Lang name="ttp_actualamount" value=""/>
<Lang name="fromxsiteid" value="起始网点"/>
<Lang name="ttp_fromxsiteid" value=""/>
<Lang name="toxsiteid" value="到达网点"/>
<Lang name="ttp_toxsiteid" value=""/>
<Lang name="customordersource" value="订单来源"/>
<Lang name="ttp_customordersource" value=""/>
<Lang name="actualbegindatetime" value="实际开始时间"/>
<Lang name="ttp_actualbegindatetime" value=""/>
<Lang name="actualenddatetime" value="实际到达时间"/>
<Lang name="ttp_actualenddatetime" value=""/>
<Lang name="appointcode" value="预约单号"/>
<Lang name="ttp_appointcode" value=""/>
<Lang name="freighttype" value="货单类型"/>
<Lang name="ttp_freighttype" value=""/>
<Lang name="haveplanned" value="是否做了调度计划"/>
<Lang name="ttp_haveplanned" value=""/>
<Lang name="freightid" value=""/>
<Lang name="ttp_freightid" value=""/>
<Lang name="createby" value=""/>
<Lang name="ttp_createby" value=""/>
<Lang name="createdate" value=""/>
<Lang name="ttp_createdate" value=""/>
<Lang name="updateby" value=""/>
<Lang name="ttp_updateby" value=""/>
<Lang name="updatedate" value=""/>
<Lang name="ttp_updatedate" value=""/>
<Lang name="ttp_operationxtmst_freight" value=""/>
<Lang name="ttp_creatextmst_freight" value=""/>
<Lang name="ttp_modifyxtmst_freight" value=""/>
<Lang name="ttp_resetxtmst_freight" value=""/>
<Lang name="ttp_deletextmst_freight" value=""/>
<Lang name="ttp_refreshxtmst_freight" value=""/>
<Lang name="operation" value=""/>
<Lang name="create" value=""/>
<Lang name="modify" value=""/>
<Lang name="reset" value=""/>
<Lang name="delete" value=""/>
<Lang name="refresh" value=""/>
<Lang name="firstpage" value=""/>
<Lang name="prepage" value=""/>
<Lang name="nextpage" value=""/>
</Language>
